wellarchitected_mcp_server/__init__.py
wellarchitected_mcp_server/server.py
wellarchitected_mcp_server/server_fixed.py
wellarchitected_mcp_server-0.1.3.dist-info/licenses/LICENSE
wellarchitected_mcp_server-0.1.3.dist-info/METADATA
wellarchitected_mcp_server-0.1.3.dist-info/WHEEL
wellarchitected_mcp_server-0.1.3.dist-info/entry_points.txt
wellarchitected_mcp_server-0.1.3.dist-info/top_level.txt
wellarchitected_mcp_server-0.1.3.dist-info/RECORD
