Metadata-Version: 2.4
Name: wellarchitected-mcp-server
Version: 0.1.3
Summary: AWS Well-Architected MCP Server for AI assistants like GitHub Copilot, AWS Q, and more
Author-email: Pratik Raut <pratik@example.com>
Maintainer-email: Pratik Raut <pratik@example.com>
License-Expression: MIT
Project-URL: Homepage, https://github.com/your-username/wellarchitected-mcp-server
Project-URL: Documentation, https://github.com/your-username/wellarchitected-mcp-server#readme
Project-URL: Repository, https://github.com/your-username/wellarchitected-mcp-server.git
Project-URL: Bug Tracker, https://github.com/your-username/wellarchitected-mcp-server/issues
Keywords: mcp,model-context-protocol,aws,well-architected,ai,assistant,copilot
Classifier: Development Status :: 4 - Beta
Classifier: Intended Audience :: Developers
Classifier: Operating System :: OS Independent
Classifier: Programming Language :: Python :: 3
Classifier: Programming Language :: Python :: 3.11
Classifier: Programming Language :: Python :: 3.12
Classifier: Topic :: Software Development :: Libraries :: Python Modules
Classifier: Topic :: System :: Systems Administration
Requires-Python: >=3.11
License-File: LICENSE
Requires-Dist: fastmcp>=2.10.0
Requires-Dist: boto3>=1.34.0
Requires-Dist: botocore>=1.34.0
Requires-Dist: typer[all]>=0.9.0
Provides-Extra: dev
Requires-Dist: pytest>=7.0.0; extra == "dev"
Requires-Dist: pytest-cov>=4.0.0; extra == "dev"
Requires-Dist: black>=23.0.0; extra == "dev"
Requires-Dist: isort>=5.12.0; extra == "dev"
Requires-Dist: flake8>=6.0.0; extra == "dev"
Requires-Dist: mypy>=1.0.0; extra == "dev"
Requires-Dist: pre-commit>=3.0.0; extra == "dev"
Dynamic: license-file
